youtube_scrapper
