Metadata-Version: 2.1
Name: Youtube-scrapper
Version: 0.0.7
Summary: A tool for extracting youtube video details
Home-page: https://github.com/VBamgbaye/Web_Scraping_Project.git
Author: Victor Bamgbaye
Author-email: bamgbayev@gmail.com
License: MIT
Platform: UNKNOWN
